<?xml version="1.0" encoding="UTF-8" standalone="yes"?>
<mets xmlns:xsi="http://www.w3.org/2001/XMLSchema-instance" 
xmlns:xlink="http://www.w3.org/1999/xlink" xmlns:mets="http://www.loc.gov/METS/" 
xmlns:csip="https://dilcis.eu/XML/METS/CSIPExtensionMETS" xmlns:sip="https://DILCIS.eu/XML/METS/SIPExtensionMETS"
xsi:schemaLocation="https://www.w3.org./1999/xlink ../../schemas/xlink.xsd http://www.loc.gov/standards/mets/xlink.xsd 
http://www.loc.gov/METS/ ../../schemas/mets.xsd
https://dilcis.eu/XML/METS/CSIPExtensionMETS ../../schemas/DILCISExtensionMETS.xsd
https://dilcis.eu/XML/METS/SIPExtensionMETS ../../schemas/DILCISExtensionSIPMETS.xsd"
PROFILE="https://data.meemoo.be/profiles/meemoo-representationmets-v1.0.x"
TYPE="OTHER" OTHERTYPE="TEXT SCRAPE" OBJID="de307969-c8f5-4395-9c20-a3441b7a3acc"
LABEL="rep-1">
    <metsHdr CREATEDATE="2021-01-17T10:59:32+02:00" csip:OAISPACKAGETYPE="SIP" />
    <amdSec ID="amd2">
        <digiprovMD ID="rep_agent">
            <mdRef LOCTYPE="URL" xlink:type="simple" xlink:href="./metadata/preservation/agent-1.xml"
            MDTYPE="PREMIS:AGENT" MIMETYPE="application/xml" SIZE="585"
            CREATED="2022-01-14T15:58:33+01:00" CHECKSUM="ef7b9646cbe2be83b724f28f98cfe75c"
            CHECKSUMTYPE="md5"></mdRef>
        </digiprovMD>
        <digiprovMD ID="rep_object">
            <mdRef LOCTYPE="URL" xlink:type="simple" xlink:href="./metadata/preservation/object-1.xml"
            MDTYPE="PREMIS:OBJECT" MIMETYPE="application/xml" SIZE="1205"
            CREATED="2022-01-14T15:58:33+01:00" CHECKSUM="515c0853269e1fe21316c737bc23c629"
            CHECKSUMTYPE="md5"></mdRef>
        </digiprovMD>
        <digiprovMD ID="rep_event">
            <mdRef LOCTYPE="URL" xlink:type="simple" xlink:href="./metadata/preservation/event-1.xml"
            MDTYPE="PREMIS:EVENT" MIMETYPE="application/xml" SIZE="1437"
            CREATED="2022-01-14T15:58:03+01:00" CHECKSUM="33d21865560cbdd335367241396b630d" CHECKSUMTYPE="md5"></mdRef>
        </digiprovMD>
    </amdSec>
    <fileSec id="fsec2">
        <fileGrp ID="data" USE="representations/rep-1/data">
            <file ID="20210325_twitter_packed_jsonl" MIMETYPE="application/json-l" SIZE="2859318" CREATED="2021-03-25T08:23+02:00" CHECKSUM="038b8ee3495eeeff908bf755eea419ed" 
            CHECKSUMTYPE="md5" ADMID="rep_object">
                <FLocat LOCTYPE="URL" xlink:type="simple" xlink:href="./data/20210325_twitter_packed_snscrape.jsonl" />
            </file>
        </fileGrp>
        <fileGrp ID="doc" USE="representations/rep-1/documentation">
            <file ID="config.yml" MIMETYPE="text/yaml" SIZE="855" CREATED="2021-03-25T08:23+02:00" CHECKSUM="02c29fef3a0a86e8a27ecd3268a557f3" 
            CHECKSUMTYPE="md5">
                <FLocat LOCTYPE="URL" xlink:type="simple" xlink:href="./documentation/config.yml" />
            </file>
        </fileGrp>
    </fileSec>
    <structMap ID="rep_structuur" TYPE="physical" LABEL="CSIP">
        <div ID="eedc92a4-85e0-478b-938a-a159c50e3147" LABEL="de307969-c8f5-4395-9c20-a3441b7a3acc">
            <div ID="2" LABEL="data">
                <fptr FILEID="data" />
            </div>
            <div ID="3" LABEL="metadata" ADMID="amd2" />
            <div ID="4" LABEL="documentation">
                <fptr FILEID="doc" />
            </div>
        </div>
    </structMap>
</mets>